queries/__init__.py
queries/pool.py
queries/results.py
queries/session.py
queries/tornado_session.py
queries/utils.py
queries-2.1.0.dist-info/LICENSE
queries-2.1.0.dist-info/METADATA
queries-2.1.0.dist-info/WHEEL
queries-2.1.0.dist-info/top_level.txt
queries-2.1.0.dist-info/zip-safe
queries-2.1.0.dist-info/RECORD
