Metadata-Version: 2.1
Name: queries
Version: 2.1.0
Summary: Simplified PostgreSQL client built upon Psycopg2
Home-page: https://github.com/gmr/queries
Maintainer: Gavin M. Roy
Maintainer-email: gavinmroy@gmail.com
License: BSD
Platform: UNKNOWN
Classifier: Development Status :: 5 - Production/Stable
Classifier: Intended Audience :: Developers
Classifier: License :: OSI Approved :: BSD License
Classifier: Operating System :: OS Independent
Classifier: Programming Language :: Python :: 2
Classifier: Programming Language :: Python :: 2.7
Classifier: Programming Language :: Python :: 3
Classifier: Programming Language :: Python :: 3.4
Classifier: Programming Language :: Python :: 3.5
Classifier: Programming Language :: Python :: 3.6
Classifier: Programming Language :: Python :: 3.7
Classifier: Programming Language :: Python :: 3.8
Classifier: Programming Language :: Python :: Implementation :: CPython
Classifier: Programming Language :: Python :: Implementation :: PyPy
Classifier: Topic :: Database
Classifier: Topic :: Software Development :: Libraries
Requires-Dist: psycopg2 (<2.9,>=2.5.1)
Provides-Extra: tornado
Requires-Dist: tornado (<6) ; extra == 'tornado'
